par_ai_core/__init__.py
par_ai_core/__main__.py
par_ai_core/llm_config.py
par_ai_core/llm_image_utils.py
par_ai_core/llm_providers.py
par_ai_core/llm_utils.py
par_ai_core/output_utils.py
par_ai_core/par_logging.py
par_ai_core/pricing_lookup.py
par_ai_core/provider_cb_info.py
par_ai_core/py.typed
par_ai_core/search_utils.py
par_ai_core/time_display.py
par_ai_core/user_agents.py
par_ai_core/utils.py
par_ai_core/web_tools.py
par_ai_core/docs/index.html
par_ai_core/docs/llm_config.html
par_ai_core/docs/llm_image_utils.html
par_ai_core/docs/llm_providers.html
par_ai_core/docs/llm_utils.html
par_ai_core/docs/output_utils.html
par_ai_core/docs/par_logging.html
par_ai_core/docs/pricing_lookup.html
par_ai_core/docs/provider_cb_info.html
par_ai_core/docs/search_utils.html
par_ai_core/docs/time_display.html
par_ai_core/docs/user_agents.html
par_ai_core/docs/utils.html
par_ai_core/docs/web_tools.html
par_ai_core-0.5.5.dist-info/METADATA
par_ai_core-0.5.5.dist-info/WHEEL
par_ai_core-0.5.5.dist-info/entry_points.txt
par_ai_core-0.5.5.dist-info/licenses/LICENSE
par_ai_core-0.5.5.dist-info/RECORD
