Metadata-Version: 2.4
Name: par_ai_core
Version: 0.5.5
Summary: PAR AI Core
Project-URL: Homepage, https://github.com/paulrobello/par_ai_core
Project-URL: Documentation, https://github.com/paulrobello/par_ai_core/blob/main/README.md
Project-URL: Repository, https://github.com/paulrobello/par_ai_core
Project-URL: Issues, https://github.com/paulrobello/par_ai_core/issues
Project-URL: Discussions, https://github.com/paulrobello/par_ai_core/discussions
Project-URL: Wiki, https://github.com/paulrobello/par_ai_core/wiki
Author-email: Paul Robello <probello@gmail.com>
Maintainer-email: Paul Robello <probello@gmail.com>
License: MIT License
License-File: LICENSE
Keywords: ai,anthropic,langchain,llamacpp,ollama,openai
Classifier: Development Status :: 4 - Beta
Classifier: Environment :: Console
Classifier: Intended Audience :: Developers
Classifier: License :: OSI Approved :: MIT License
Classifier: Operating System :: MacOS
Classifier: Operating System :: Microsoft :: Windows :: Windows 10
Classifier: Operating System :: Microsoft :: Windows :: Windows 11
Classifier: Programming Language :: Python :: 3
Classifier: Programming Language :: Python :: 3.11
Classifier: Programming Language :: Python :: 3.12
Classifier: Programming Language :: Python :: 3.13
Classifier: Programming Language :: Python :: 3.14
Classifier: Topic :: Software Development :: Libraries :: Python Modules
Classifier: Typing :: Typed
Requires-Python: >=3.11
Requires-Dist: beautifulsoup4>=4.14.2
Requires-Dist: boto3>=1.40.58
Requires-Dist: botocore>=1.40.58
Requires-Dist: html2text>=2025.4.15
Requires-Dist: langchain-anthropic>=1.0.0
Requires-Dist: langchain-aws>=1.0.0
Requires-Dist: langchain-community>=0.4.0
Requires-Dist: langchain-core>=1.0.0
Requires-Dist: langchain-deepseek>=1.0.0
Requires-Dist: langchain-experimental>=0.4.0
Requires-Dist: langchain-google-community>=3.0.0
Requires-Dist: langchain-google-genai>=3.0.0
Requires-Dist: langchain-groq>=1.0.0
Requires-Dist: langchain-mistralai>=1.0.0
Requires-Dist: langchain-ollama>=1.0.0
Requires-Dist: langchain-openai>=1.0.0
Requires-Dist: langchain-text-splitters>=1.0.0
Requires-Dist: langchain-xai>=1.0.0
Requires-Dist: langchain>=1.0.0
Requires-Dist: langgraph>=1.0.1
Requires-Dist: litellm>=1.78.7
Requires-Dist: markdownify>=1.2.0
Requires-Dist: nest-asyncio>=1.6.0
Requires-Dist: openai>=1.99.9
Requires-Dist: orjson>=3.11.4
Requires-Dist: playwright>=1.55.0
Requires-Dist: praw>=7.8.1
Requires-Dist: pydantic-core>=2.33.2
Requires-Dist: pydantic>=2.11.4
Requires-Dist: python-dotenv>=1.1.1
Requires-Dist: requests>=2.32.5
Requires-Dist: rich>=14.2.0
Requires-Dist: selenium>=4.37.0
Requires-Dist: strenum>=0.4.15
Requires-Dist: tavily-python>=0.7.12
Requires-Dist: webdriver-manager>=4.0.2
Requires-Dist: youtube-transcript-api>=1.2.3
